LICENSE.txt
MANIFEST.in
README.md
setup.py
.eggs/README.txt
.eggs/setuptools_git-1.2-py2.7.egg
vaksana_proto/.gitignore
vaksana_proto/README.md
vaksana_proto/__init__.py
vaksana_proto/build.sh
vaksana_proto/intent.proto
vaksana_proto/intent_pb2.py
vaksana_proto/intent_pb2_grpc.py
vaksana_proto/mongo.proto
vaksana_proto/mongo_pb2.py
vaksana_proto/mongo_pb2_grpc.py
vaksana_proto/redisclient.proto
vaksana_proto/redisclient_pb2.py
vaksana_proto/redisclient_pb2_grpc.py
vaksana_proto/ssl.proto
vaksana_proto/ssl_pb2.py
vaksana_proto/ssl_pb2_grpc.py
vaksana_proto/stub.proto
vaksana_proto/stub_pb2.py
vaksana_proto/stub_pb2_grpc.py
vaksana_proto/vaksana.proto
vaksana_proto/vaksana_pb2.py
vaksana_proto/vaksana_pb2_grpc.py
vaksana_proto.egg-info/PKG-INFO
vaksana_proto.egg-info/SOURCES.txt
vaksana_proto.egg-info/dependency_links.txt
vaksana_proto.egg-info/requires.txt
vaksana_proto.egg-info/top_level.txt